odoo/addons/purchase_warn_message/README.rst
odoo/addons/purchase_warn_message/__init__.py
odoo/addons/purchase_warn_message/__manifest__.py
odoo/addons/purchase_warn_message/i18n/purchase_warn_message.pot
odoo/addons/purchase_warn_message/models/__init__.py
odoo/addons/purchase_warn_message/models/purchase_order.py
odoo/addons/purchase_warn_message/readme/CONTRIBUTORS.rst
odoo/addons/purchase_warn_message/readme/DESCRIPTION.rst
odoo/addons/purchase_warn_message/static/description/icon.png
odoo/addons/purchase_warn_message/static/description/index.html
odoo/addons/purchase_warn_message/tests/__init__.py
odoo/addons/purchase_warn_message/tests/test_purchase_warn_message.py
odoo/addons/purchase_warn_message/views/purchase_order_views.xml
odoo13_addon_purchase_warn_message-13.0.1.0.3.dist-info/METADATA
odoo13_addon_purchase_warn_message-13.0.1.0.3.dist-info/WHEEL
odoo13_addon_purchase_warn_message-13.0.1.0.3.dist-info/top_level.txt
odoo13_addon_purchase_warn_message-13.0.1.0.3.dist-info/RECORD
